MANIFEST.in
setup.cfg
setup.py
vhostino/__init__.py
vhostino/plugin.py
vhostino/server.py
vhostino.egg-info/PKG-INFO
vhostino.egg-info/SOURCES.txt
vhostino.egg-info/dependency_links.txt
vhostino.egg-info/entry_points.txt
vhostino.egg-info/not-zip-safe
vhostino.egg-info/requires.txt
vhostino.egg-info/top_level.txt