Metadata-Version: 1.0
Name: vhostino
Version: 0.0.1
Summary: Virtual Hosts Plugin for Mozilla Circus
Home-page: https://github.com/amol-/vhostino
Author: Alessandro Molina
Author-email: amol@turbogears.org
License: MIT
Platform: UNKNOWN
